cis_checks_10/__init__.py
cis_checks_10/iam_control_1.py
cis_checks_10/logging_control_2.py
cis_checks_10/monitoring_control_3.py
cis_checks_10/networking_control_4.py
cis_checks_10/security_control_5.py
cis_checks_10/utils.py
cis_checks_10-0.0.11.dist-info/METADATA
cis_checks_10-0.0.11.dist-info/WHEEL
cis_checks_10-0.0.11.dist-info/top_level.txt
cis_checks_10-0.0.11.dist-info/RECORD
